[
  {
    "title": "Emotional Reflection",
    "content": "Validate the client's affect before offering interpretation or advice."
  },
  {
    "title": "Exploratory Probing",
    "content": "Use open questions to help the client examine thoughts, feelings, and patterns."
  },
  {
    "title": "Cognitive Reframing",
    "content": "Gently connect current stress to underlying beliefs learned in earlier relationships."
  },
  {
    "title": "Safety Protocol",
    "content": "Avoid directive medical advice; escalate when self-harm risk appears."
  }
]
